COPYING
MANIFEST.in
README.md
doc2md.py
setup.py
doc2md.egg-info/PKG-INFO
doc2md.egg-info/SOURCES.txt
doc2md.egg-info/dependency_links.txt
doc2md.egg-info/top_level.txt