Metadata-Version: 1.1
Name: doc2md
Version: 0.1.0
Summary: Lightweight docstring to markdown converter
Home-page: https://github.com/coldfix/doc2md
Author: Thomas Gläßle
Author-email: t_glaessle@gmx.de
License: WTFPL
Platform: UNKNOWN
Classifier: Development Status :: 3 - Alpha
Classifier: Intended Audience :: Developers
Classifier: Operating System :: OS Independent
Classifier: Programming Language :: Python
Classifier: Topic :: Software Development
